<dialogue>
	<node>
		<face>0</face>
		<name>Семен</name>
		<text>Так-то лучше. Текс, что у нас по времени. Надо бы поторапливаться. Все-таки первый рабочий день, на первой работе. Ну как рабочий, собеседование скорее всего, но что это меняет? Я должен произвести хорошее впечатление. Так соберись, соберись, вдох-выдох. Все нормально, просто приди и докажи им, что они не ошиблись в твоей кандидатуре. Тебе нужна эта работа мужик и ты ее получишь. Не зря же проехал пол страны, не зря. Все, рванули!</text>
		<nextNode>0</nextNode>
		<dialend>true</dialend>
	</node>
</dialogue>